rkgb/Atools.py
rkgb/Btools.py
rkgb/Dtools.py
rkgb/Ktools.py
rkgb/Stools.py
rkgb/__init__.py
rkgb/main.py
rkgb/utils/__init__.py
rkgb/utils/ast_add_on.py
rkgb/utils/complement_for_Stools.py
rkgb/utils/def_info.py
rkgb/utils/def_inspection.py
rkgb/utils/global_vars.py
rkgb/utils/imports.py
rkgb/utils/imports_from_rotor.py
rkgb/utils/shared_methods.py
rkgb/utils/small_fcts.py
rkgb-1.0.1.dist-info/LICENSE.txt
rkgb-1.0.1.dist-info/METADATA
rkgb-1.0.1.dist-info/WHEEL
rkgb-1.0.1.dist-info/top_level.txt
rkgb-1.0.1.dist-info/RECORD
