Metadata-Version: 2.1
Name: rkgb
Version: 1.0.1
Summary: Graph Builder tool of the Rockmate package
Author: Théotime Le Hellard, Xunyi Zhao, Julia Gusak, Olivier Beaumont, Lionel Eyraud-Dubois
Maintainer-email: Lionel Eyraud-Dubois <lionel.eyraud-dubois@inria.fr>
License: GNU GENERAL PUBLIC LICENSE
Project-URL: Repository, https://github.com/topal-team/rockmate.git
Keywords: vizualisation,pytorch
Requires-Python: >=3.8
License-File: LICENSE.txt
Requires-Dist: numpy
Requires-Dist: torch (>=1.8)
Requires-Dist: astunparse (>=1.6.3)
Provides-Extra: draw
Requires-Dist: pygraphviz ; extra == 'draw'
